{
  "ComponentIndexes": {},
  "ControlUniqueGuids": {},
  "ControlUniqueIds": {
    "¿Aceptas los términos y condiciones?_DataCard2": 87,
    "App": 1,
    "Bienvenidos": 51,
    "BrowseGallery1": 196,
    "Button1": 140,
    "Button1_1": 148,
    "Button2": 12,
    "Button3": 141,
    "Button4": 151,
    "Button5": 53,
    "Configuraciones": 212,
    "constrasena": 9,
    "Contraseña_DataCard2": 82,
    "Correo_DataCard2": 77,
    "Create_account": 59,
    "DataCardKey10": 106,
    "DataCardKey11": 111,
    "DataCardKey12": 116,
    "DataCardKey13": 121,
    "DataCardKey14": 126,
    "DataCardKey14_1": 64,
    "DataCardKey15": 131,
    "DataCardKey15_1": 69,
    "DataCardKey16": 136,
    "DataCardKey16_1": 74,
    "DataCardKey17": 79,
    "DataCardKey18": 84,
    "DataCardKey19": 89,
    "DataCardKey2": 31,
    "DataCardKey4": 24,
    "DataCardKey5": 29,
    "DataCardKey6": 34,
    "DataCardKey8": 37,
    "DataCardKey9": 101,
    "DataCardValue10": 107,
    "DataCardValue11": 112,
    "DataCardValue12": 117,
    "DataCardValue13": 122,
    "DataCardValue14": 127,
    "DataCardValue14_1": 65,
    "DataCardValue15": 132,
    "DataCardValue15_1": 70,
    "DataCardValue16": 137,
    "DataCardValue16_1": 75,
    "DataCardValue17": 80,
    "DataCardValue18": 85,
    "DataCardValue19": 88,
    "DataCardValue2": 32,
    "DataCardValue4": 26,
    "DataCardValue5": 28,
    "DataCardValue6": 35,
    "DataCardValue8": 38,
    "DataCardValue9": 102,
    "DetailForm1": 22,
    "Edit[no oficial en pruevas]": 93,
    "EditForm1": 98,
    "Error Loging": 139,
    "ErrorMessage1": 103,
    "ErrorMessage11": 66,
    "ErrorMessage12": 71,
    "ErrorMessage13": 76,
    "ErrorMessage14": 81,
    "ErrorMessage15": 86,
    "ErrorMessage2": 108,
    "ErrorMessage3": 113,
    "ErrorMessage4": 118,
    "ErrorMessage5": 123,
    "ErrorMessage6": 128,
    "ErrorMessage7": 133,
    "ErrorMessage8": 138,
    "Exito Signup": 147,
    "Form3": 61,
    "Fuente_DataCard2": 129,
    "Gallery3": 45,
    "galleryTemplate1": 197,
    "galleryTemplate4": 46,
    "Genero_DataCard1": 33,
    "Genero_DataCard2": 124,
    "Home": 155,
    "Host": 3,
    "Icon1": 158,
    "Icon2": 183,
    "Icon2_1": 206,
    "Icon2_2": 19,
    "Icon2_3": 227,
    "Icon3": 157,
    "Icon4": 156,
    "Icon5": 182,
    "Icon5_1": 205,
    "Icon5_2": 16,
    "Icon5_3": 228,
    "Icon6": 184,
    "Icon6_1": 207,
    "Icon6_2": 39,
    "Icon6_3": 229,
    "Icon7": 143,
    "Icon8": 152,
    "Icon9": 216,
    "IconAccept1": 96,
    "IconBackarrow1": 15,
    "IconCancel1": 95,
    "IconDelete1": 18,
    "IconEdit1": 20,
    "IconNewItem1": 193,
    "IconRefresh1": 191,
    "IconSortUpDown1": 192,
    "Id_lista_DataCard2": 99,
    "Image[image]_DataCard2": 109,
    "Image1": 213,
    "Image2": 198,
    "Image2_1": 174,
    "Image2_2": 164,
    "Image2_3": 172,
    "Image2_4": 170,
    "Image2_5": 165,
    "Image2_6": 178,
    "Image3": 175,
    "Image3_1": 179,
    "Image3_2": 180,
    "Image4": 176,
    "Image6": 55,
    "Inicio de sesión": 11,
    "Interprete_DataCard1": 27,
    "Interprete_DataCard2": 119,
    "Label1": 214,
    "Label1_3": 56,
    "Label1_4": 187,
    "Label1_5": 211,
    "Label1_6": 42,
    "Label1_7": 226,
    "Label10": 215,
    "Label11": 54,
    "Label12": 21,
    "Label13": 217,
    "Label14": 218,
    "Label15": 219,
    "Label15_1": 221,
    "Label15_2": 223,
    "Label16": 220,
    "Label16_1": 222,
    "Label2": 5,
    "Label2_2": 60,
    "Label3": 6,
    "Label3_1": 8,
    "Label4": 90,
    "Label4_1": 185,
    "Label4_2": 208,
    "Label4_3": 40,
    "Label4_4": 230,
    "Label5": 186,
    "Label5_1": 209,
    "Label5_2": 210,
    "Label5_3": 41,
    "Label5_4": 231,
    "Label6": 144,
    "Label6_1": 150,
    "Label7": 142,
    "Label7_1": 149,
    "Label8": 160,
    "Label9": 166,
    "Label9_1": 163,
    "Label9_2": 171,
    "Label9_3": 169,
    "LblAppName1": 190,
    "LblAppName2": 17,
    "LblAppName3": 97,
    "Libreria": 188,
    "Log_in": 4,
    "Momento_DataCard1": 30,
    "Momento_DataCard2": 104,
    "NextArrow3": 200,
    "NextArrow4": 49,
    "Nombre_DataCard2": 67,
    "NombreC_DataCard1": 23,
    "NombreC_DataCard2": 114,
    "olvidar": 10,
    "Rectangle1": 161,
    "Rectangle11": 203,
    "Rectangle2": 162,
    "Rectangle3": 167,
    "Rectangle4": 168,
    "Rectangle5": 52,
    "Rectangle6": 159,
    "RectQuickActionBar1": 189,
    "RectQuickActionBar2": 14,
    "RectQuickActionBar3": 94,
    "Registrar_1": 91,
    "Relato_DataCard1": 36,
    "Relato_DataCard2": 134,
    "Reproductor": 13,
    "Screen2": 44,
    "SearchIcon1": 195,
    "Separator3": 202,
    "Separator4": 50,
    "StarVisible1": 100,
    "StarVisible11": 63,
    "StarVisible12": 68,
    "StarVisible13": 73,
    "StarVisible14": 78,
    "StarVisible15": 83,
    "StarVisible2": 105,
    "StarVisible3": 110,
    "StarVisible4": 115,
    "StarVisible5": 120,
    "StarVisible6": 125,
    "StarVisible7": 130,
    "StarVisible8": 135,
    "Subtitle2": 201,
    "Subtitle4": 48,
    "Teléfono _DataCard2": 72,
    "TextInput1": 173,
    "TextInput1_1": 181,
    "TextInput1_10": 58,
    "TextInput1_11": 224,
    "TextInput1_12": 225,
    "TextInput1_2": 177,
    "TextInput1_3": 204,
    "TextInput1_4": 43,
    "TextInput1_5": 57,
    "TextInput1_6": 145,
    "TextInput1_7": 146,
    "TextInput1_8": 153,
    "TextInput1_9": 154,
    "TextSearchBox1": 194,
    "Title3": 199,
    "Title4": 47,
    "Título_DataCard2": 62,
    "usuario": 7,
    "Video1": 25,
    "volver_2": 92
  },
  "FunctionParamsInvariantScripts": {},
  "FunctionParamsInvariantScriptsOnInstances": {},
  "HeaderLastSavedDateTimeUTC": "06/05/2023 05:42:06",
  "IsLegacyComponentAllowGlobalScopeCase": false,
  "LocalConnectionIDReferences": {
    "599b1913-4d6c-430e-8b80-6f1264943d5c": "\"/providers/microsoft.powerapps/apis/shared_sharepointonline/connections/4c285b6d2a1d4a5fa9f8e8a2908d8f3b\""
  },
  "LocalDatabaseReferencesAsEmpty": false,
  "LocalResourceFileNames": {
    "logo (1)": "0001.png"
  },
  "LocalResourceRootPaths": {
    "logo (1)": "https://docserverpwaprodeus.blob.core.windows.net/9138c859-61c2-4c7a-a637-3000f07bb066-1/resource/Assets0Images00001.png?sv=2018-03-28&sr=b&sig=WZxoOIc%2BOdC359njNpfXCaKMcpcxsHZ%2FefR79yPl47o%3D&spr=https&se=2023-06-06T05%3A40%3A59Z&sp=r"
  },
  "OldLogoFileName": "logo.jpg",
  "OrderComponentMetadata": {},
  "OrderComponentTemplate": {},
  "OrderDataSource": {
    "CustomGallerySample": 0,
    "luna's_songs": 1,
    "m": 2,
    "registro": 3
  },
  "OrderGroupControls": {},
  "OrderPcfTemplate": {},
  "OrderTemplate": {},
  "OrderXMLTemplate": {
    "button": 2,
    "form": 9,
    "formViewer": 5,
    "gallery": 7,
    "icon": 4,
    "image": 8,
    "label": 0,
    "rectangle": 3,
    "text": 1,
    "toggleSwitch": 10,
    "videoPlayback": 6
  },
  "OverridablePropertiesEntry": {
    "¿Aceptas los términos y condiciones?_DataCard2": {},
    "App": {},
    "Bienvenidos": {},
    "BrowseGallery1": {},
    "Button1": {},
    "Button1_1": {},
    "Button2": {},
    "Button3": {},
    "Button4": {},
    "Button5": {},
    "Configuraciones": {},
    "constrasena": {},
    "Contraseña_DataCard2": {},
    "Correo_DataCard2": {},
    "Create_account": {},
    "DataCardKey10": {},
    "DataCardKey11": {},
    "DataCardKey12": {},
    "DataCardKey13": {},
    "DataCardKey14": {},
    "DataCardKey14_1": {},
    "DataCardKey15": {},
    "DataCardKey15_1": {},
    "DataCardKey16": {},
    "DataCardKey16_1": {},
    "DataCardKey17": {},
    "DataCardKey18": {},
    "DataCardKey19": {},
    "DataCardKey2": {},
    "DataCardKey4": {},
    "DataCardKey5": {},
    "DataCardKey6": {},
    "DataCardKey8": {},
    "DataCardKey9": {},
    "DataCardValue10": {},
    "DataCardValue11": {},
    "DataCardValue12": {},
    "DataCardValue13": {},
    "DataCardValue14": {},
    "DataCardValue14_1": {},
    "DataCardValue15": {},
    "DataCardValue15_1": {},
    "DataCardValue16": {},
    "DataCardValue16_1": {},
    "DataCardValue17": {},
    "DataCardValue18": {},
    "DataCardValue19": {},
    "DataCardValue2": {},
    "DataCardValue4": {},
    "DataCardValue5": {},
    "DataCardValue6": {},
    "DataCardValue8": {},
    "DataCardValue9": {},
    "DetailForm1": {},
    "Edit[no oficial en pruevas]": {},
    "EditForm1": {},
    "Error Loging": {},
    "ErrorMessage1": {},
    "ErrorMessage11": {},
    "ErrorMessage12": {},
    "ErrorMessage13": {},
    "ErrorMessage14": {},
    "ErrorMessage15": {},
    "ErrorMessage2": {},
    "ErrorMessage3": {},
    "ErrorMessage4": {},
    "ErrorMessage5": {},
    "ErrorMessage6": {},
    "ErrorMessage7": {},
    "ErrorMessage8": {},
    "Exito Signup": {},
    "Form3": {},
    "Fuente_DataCard2": {},
    "Gallery3": {},
    "galleryTemplate1": {},
    "galleryTemplate4": {},
    "Genero_DataCard1": {},
    "Genero_DataCard2": {},
    "Home": {},
    "Host": {},
    "Icon1": {},
    "Icon2": {},
    "Icon2_1": {},
    "Icon2_2": {},
    "Icon2_3": {},
    "Icon3": {},
    "Icon4": {},
    "Icon5": {},
    "Icon5_1": {},
    "Icon5_2": {},
    "Icon5_3": {},
    "Icon6": {},
    "Icon6_1": {},
    "Icon6_2": {},
    "Icon6_3": {},
    "Icon7": {},
    "Icon8": {},
    "Icon9": {},
    "IconAccept1": {},
    "IconBackarrow1": {},
    "IconCancel1": {},
    "IconDelete1": {},
    "IconEdit1": {},
    "IconNewItem1": {},
    "IconRefresh1": {},
    "IconSortUpDown1": {},
    "Id_lista_DataCard2": {},
    "Image[image]_DataCard2": {},
    "Image1": {},
    "Image2": {},
    "Image2_1": {},
    "Image2_2": {},
    "Image2_3": {},
    "Image2_4": {},
    "Image2_5": {},
    "Image2_6": {},
    "Image3": {},
    "Image3_1": {},
    "Image3_2": {},
    "Image4": {},
    "Image6": {},
    "Inicio de sesión": {},
    "Interprete_DataCard1": {},
    "Interprete_DataCard2": {},
    "Label1": {},
    "Label1_3": {},
    "Label1_4": {},
    "Label1_5": {},
    "Label1_6": {},
    "Label1_7": {},
    "Label10": {},
    "Label11": {},
    "Label12": {},
    "Label13": {},
    "Label14": {},
    "Label15": {},
    "Label15_1": {},
    "Label15_2": {},
    "Label16": {},
    "Label16_1": {},
    "Label2": {},
    "Label2_2": {},
    "Label3": {},
    "Label3_1": {},
    "Label4": {},
    "Label4_1": {},
    "Label4_2": {},
    "Label4_3": {},
    "Label4_4": {},
    "Label5": {},
    "Label5_1": {},
    "Label5_2": {},
    "Label5_3": {},
    "Label5_4": {},
    "Label6": {},
    "Label6_1": {},
    "Label7": {},
    "Label7_1": {},
    "Label8": {},
    "Label9": {},
    "Label9_1": {},
    "Label9_2": {},
    "Label9_3": {},
    "LblAppName1": {},
    "LblAppName2": {},
    "LblAppName3": {},
    "Libreria": {},
    "Log_in": {},
    "Momento_DataCard1": {},
    "Momento_DataCard2": {},
    "NextArrow3": {},
    "NextArrow4": {},
    "Nombre_DataCard2": {},
    "NombreC_DataCard1": {},
    "NombreC_DataCard2": {},
    "olvidar": {},
    "Rectangle1": {},
    "Rectangle11": {},
    "Rectangle2": {},
    "Rectangle3": {},
    "Rectangle4": {},
    "Rectangle5": {},
    "Rectangle6": {},
    "RectQuickActionBar1": {},
    "RectQuickActionBar2": {},
    "RectQuickActionBar3": {},
    "Registrar_1": {},
    "Relato_DataCard1": {},
    "Relato_DataCard2": {},
    "Reproductor": {},
    "Screen2": {},
    "SearchIcon1": {},
    "Separator3": {},
    "Separator4": {},
    "StarVisible1": {},
    "StarVisible11": {},
    "StarVisible12": {},
    "StarVisible13": {},
    "StarVisible14": {},
    "StarVisible15": {},
    "StarVisible2": {},
    "StarVisible3": {},
    "StarVisible4": {},
    "StarVisible5": {},
    "StarVisible6": {},
    "StarVisible7": {},
    "StarVisible8": {},
    "Subtitle2": {},
    "Subtitle4": {},
    "Teléfono _DataCard2": {},
    "TextInput1": {},
    "TextInput1_1": {},
    "TextInput1_10": {},
    "TextInput1_11": {},
    "TextInput1_12": {},
    "TextInput1_2": {},
    "TextInput1_3": {},
    "TextInput1_4": {},
    "TextInput1_5": {},
    "TextInput1_6": {},
    "TextInput1_7": {},
    "TextInput1_8": {},
    "TextInput1_9": {},
    "TextSearchBox1": {},
    "Title3": {},
    "Title4": {},
    "Título_DataCard2": {},
    "usuario": {},
    "Video1": {},
    "volver_2": {}
  },
  "PCFDynamicSchemaForIRRetrievalEntry": {},
  "PCFTemplateEntry": {},
  "PublishOrderIndices": {
    "¿Aceptas los términos y condiciones?_DataCard2": 42,
    "App": 0,
    "Bienvenidos": 3,
    "BrowseGallery1": 87,
    "Button1": 178,
    "Button1_1": 185,
    "Button2": 14,
    "Button3": 183,
    "Button4": 190,
    "Button5": 4,
    "Configuraciones": 0,
    "constrasena": 11,
    "Contraseña_DataCard2": 37,
    "Correo_DataCard2": 32,
    "Create_account": 11,
    "DataCardKey10": 145,
    "DataCardKey11": 150,
    "DataCardKey12": 155,
    "DataCardKey13": 160,
    "DataCardKey14": 165,
    "DataCardKey14_1": 19,
    "DataCardKey15": 170,
    "DataCardKey15_1": 24,
    "DataCardKey16": 175,
    "DataCardKey16_1": 29,
    "DataCardKey17": 34,
    "DataCardKey18": 39,
    "DataCardKey19": 44,
    "DataCardKey2": 117,
    "DataCardKey4": 110,
    "DataCardKey5": 115,
    "DataCardKey6": 120,
    "DataCardKey8": 123,
    "DataCardKey9": 140,
    "DataCardValue10": 146,
    "DataCardValue11": 151,
    "DataCardValue12": 156,
    "DataCardValue13": 161,
    "DataCardValue14": 166,
    "DataCardValue14_1": 20,
    "DataCardValue15": 171,
    "DataCardValue15_1": 25,
    "DataCardValue16": 176,
    "DataCardValue16_1": 30,
    "DataCardValue17": 35,
    "DataCardValue18": 40,
    "DataCardValue19": 43,
    "DataCardValue2": 118,
    "DataCardValue4": 112,
    "DataCardValue5": 114,
    "DataCardValue6": 121,
    "DataCardValue8": 124,
    "DataCardValue9": 141,
    "DetailForm1": 108,
    "Edit[no oficial en pruevas]": 45,
    "EditForm1": 137,
    "Error Loging": 91,
    "ErrorMessage1": 142,
    "ErrorMessage11": 21,
    "ErrorMessage12": 26,
    "ErrorMessage13": 31,
    "ErrorMessage14": 36,
    "ErrorMessage15": 41,
    "ErrorMessage2": 147,
    "ErrorMessage3": 152,
    "ErrorMessage4": 157,
    "ErrorMessage5": 162,
    "ErrorMessage6": 167,
    "ErrorMessage7": 172,
    "ErrorMessage8": 177,
    "Exito Signup": 99,
    "Form3": 16,
    "Fuente_DataCard2": 168,
    "Gallery3": 192,
    "galleryTemplate1": 88,
    "galleryTemplate4": 193,
    "Genero_DataCard1": 119,
    "Genero_DataCard2": 163,
    "Home": 107,
    "Host": 0,
    "Icon1": 50,
    "Icon2": 75,
    "Icon2_1": 97,
    "Icon2_2": 128,
    "Icon2_3": 212,
    "Icon3": 49,
    "Icon4": 48,
    "Icon5": 74,
    "Icon5_1": 96,
    "Icon5_2": 127,
    "Icon5_3": 211,
    "Icon6": 76,
    "Icon6_1": 98,
    "Icon6_2": 129,
    "Icon6_3": 213,
    "Icon7": 182,
    "Icon8": 189,
    "Icon9": 201,
    "IconAccept1": 136,
    "IconBackarrow1": 104,
    "IconCancel1": 134,
    "IconDelete1": 106,
    "IconEdit1": 107,
    "IconNewItem1": 84,
    "IconRefresh1": 82,
    "IconSortUpDown1": 83,
    "Id_lista_DataCard2": 138,
    "Image[image]_DataCard2": 148,
    "Image1": 200,
    "Image2": 89,
    "Image2_1": 66,
    "Image2_2": 56,
    "Image2_3": 64,
    "Image2_4": 62,
    "Image2_5": 57,
    "Image2_6": 70,
    "Image3": 67,
    "Image3_1": 71,
    "Image3_2": 72,
    "Image4": 68,
    "Image6": 3,
    "Inicio de sesión": 13,
    "Interprete_DataCard1": 113,
    "Interprete_DataCard2": 158,
    "Label1": 199,
    "Label1_3": 6,
    "Label1_4": 79,
    "Label1_5": 102,
    "Label1_6": 132,
    "Label1_7": 216,
    "Label10": 202,
    "Label11": 2,
    "Label12": 125,
    "Label13": 203,
    "Label14": 204,
    "Label15": 205,
    "Label15_1": 207,
    "Label15_2": 209,
    "Label16": 206,
    "Label16_1": 208,
    "Label2": 7,
    "Label2_2": 15,
    "Label3": 8,
    "Label3_1": 10,
    "Label4": 45,
    "Label4_1": 77,
    "Label4_2": 99,
    "Label4_3": 130,
    "Label4_4": 214,
    "Label5": 78,
    "Label5_1": 100,
    "Label5_2": 101,
    "Label5_3": 131,
    "Label5_4": 215,
    "Label6": 181,
    "Label6_1": 188,
    "Label7": 180,
    "Label7_1": 187,
    "Label8": 52,
    "Label9": 58,
    "Label9_1": 55,
    "Label9_2": 63,
    "Label9_3": 61,
    "LblAppName1": 81,
    "LblAppName2": 105,
    "LblAppName3": 135,
    "Libreria": 140,
    "Log_in": 164,
    "Momento_DataCard1": 116,
    "Momento_DataCard2": 143,
    "NextArrow3": 91,
    "NextArrow4": 195,
    "Nombre_DataCard2": 22,
    "NombreC_DataCard1": 109,
    "NombreC_DataCard2": 153,
    "olvidar": 12,
    "Rectangle1": 53,
    "Rectangle11": 94,
    "Rectangle2": 54,
    "Rectangle3": 59,
    "Rectangle4": 60,
    "Rectangle5": 1,
    "Rectangle6": 51,
    "RectQuickActionBar1": 80,
    "RectQuickActionBar2": 103,
    "RectQuickActionBar3": 133,
    "Registrar_1": 46,
    "Relato_DataCard1": 122,
    "Relato_DataCard2": 173,
    "Reproductor": 173,
    "Screen2": 204,
    "SearchIcon1": 86,
    "Separator3": 93,
    "Separator4": 197,
    "StarVisible1": 139,
    "StarVisible11": 18,
    "StarVisible12": 23,
    "StarVisible13": 28,
    "StarVisible14": 33,
    "StarVisible15": 38,
    "StarVisible2": 144,
    "StarVisible3": 149,
    "StarVisible4": 154,
    "StarVisible5": 159,
    "StarVisible6": 164,
    "StarVisible7": 169,
    "StarVisible8": 174,
    "Subtitle2": 92,
    "Subtitle4": 196,
    "Teléfono _DataCard2": 27,
    "TextInput1": 65,
    "TextInput1_1": 73,
    "TextInput1_10": 0,
    "TextInput1_11": 210,
    "TextInput1_12": 198,
    "TextInput1_2": 69,
    "TextInput1_3": 95,
    "TextInput1_4": 126,
    "TextInput1_5": 5,
    "TextInput1_6": 184,
    "TextInput1_7": 179,
    "TextInput1_8": 191,
    "TextInput1_9": 186,
    "TextSearchBox1": 85,
    "Title3": 90,
    "Title4": 194,
    "Título_DataCard2": 17,
    "usuario": 9,
    "Video1": 111,
    "volver_2": 47
  },
  "ResourcesJsonIndices": {
    "Audio-SampleAudio": 0,
    "Image-logo (1)": 3,
    "Image-SampleImage": 1,
    "Video-SampleVideo": 2
  },
  "RuleScreenIdWithoutScreen": {},
  "TemplateVersions": {},
  "VolatileProperties": {
    "AnalysisLoadTime": 0.5650894,
    "ControlCount": {
      "button": 10,
      "form": 2,
      "formViewer": 1,
      "gallery": 2,
      "galleryTemplate": 2,
      "icon": 28,
      "image": 12,
      "label": 90,
      "rectangle": 12,
      "screen": 10,
      "text": 29,
      "toggleSwitch": 1,
      "typedDataCard": 19,
      "videoPlayback": 1
    },
    "DeserializationLoadTime": 0.9772143
  },
  "WasLocalDatabaseReferencesEmpty": true
}